scores/__init__.py
scores/_cache_utils.py
scores/scores.py
scores/models/__init__.py
scores/models/competition.py
scores/models/competitor.py
scores/models/game.py
scores/models/game_asset.py
scores/models/game_assets.py
scores/models/game_competitor.py
scores/models/base/__init__.py
scores/models/base/base_competing_object.py
scores/models/base/country.py
scores/models/base/sport.py
scores/models/base/core/__init__.py
scores/models/base/core/base_idable.py
scores/models/base/core/base_object.py
scores/models/base/core/enums/__init__.py
scores/models/base/core/enums/sport_type.py
365scores-1.0.7.dist-info/METADATA
365scores-1.0.7.dist-info/WHEEL
365scores-1.0.7.dist-info/top_level.txt
365scores-1.0.7.dist-info/RECORD
