Metadata-Version: 2.1
Name: 365scores
Version: 1.0.7
Summary: 365scores
Home-page: https://github.com/kkristof200/py_365scores
Author: Kristof
License: UNKNOWN
Platform: UNKNOWN
Classifier: Programming Language :: Python :: 3
Classifier: License :: OSI Approved :: MIT License
Classifier: Operating System :: OS Independent
Requires-Python: >=3.5
Requires-Dist: jsoncodable
Requires-Dist: kcu
Requires-Dist: ksimpleapi
Requires-Dist: simple-multiprocessing
